LICENSE
README.md
setup.cfg
setup.py
twocaptcha_extension_python/__init__.py
twocaptcha_extension_python.egg-info/PKG-INFO
twocaptcha_extension_python.egg-info/SOURCES.txt
twocaptcha_extension_python.egg-info/dependency_links.txt
twocaptcha_extension_python.egg-info/requires.txt
twocaptcha_extension_python.egg-info/top_level.txt