Metadata-Version: 2.1
Name: twocaptcha_extension_python
Version: 1.0.1
Summary: TwoCaptcha Extension Python allows you to easily integrate TwoCaptcha Extension in web automation frameworks like Botasaurus, Selenium, and Playwright.
Home-page: https://github.com/omkarcloud/twocaptcha-extension-python
Author: Chetan Jain
Author-email: chetan@omkar.cloud
License: MIT
Keywords: twocaptcha-extension-python
Classifier: Development Status :: 5 - Production/Stable
Classifier: Topic :: Software Development :: Testing
Classifier: Topic :: System :: Installation/Setup
Classifier: Topic :: Software Development :: Libraries :: Python Modules
Classifier: License :: OSI Approved :: MIT License
Classifier: Programming Language :: Python :: 3
Classifier: Programming Language :: Python :: 3.6
Classifier: Programming Language :: Python :: 3.7
Classifier: Programming Language :: Python :: 3.8
Classifier: Programming Language :: Python :: 3.9
Classifier: Programming Language :: Python :: 3.10
Requires-Python: >=3.6
License-File: LICENSE
Requires-Dist: chrome_extension_python
